[
    {
        "id": "8380054379",
        "owner": "34368269@N04",
        "secret": "cca75b9eff",
        "server": "8087",
        "farm": 9,
        "title": "White-tailed Kite",
        "ispublic": 1,
        "isfriend": 0,
        "isfamily": 0,
        "latitude": 38.500134,
        "longitude": -121.695114,
        "accuracy": "16",
        "context": 0,
        "place_id": "xB7pD8NTUbI3JLZ_",
        "woeid": "2389646",
        "geo_is_family": 0,
        "geo_is_friend": 0,
        "geo_is_contact": 0,
        "geo_is_public": 1,
        "tags": "california nature birds northerncalifornia birdsofprey centralvalley whitetailedkite elanusleucurrus"
    },
    {
        "id": "8715333780",
        "owner": "8552398@N03",
        "secret": "facfd83b1d",
        "server": "7424",
        "farm": 8,
        "title": "5_6_13",
        "ispublic": 1,
        "isfriend": 0,
        "isfamily": 0,
        "latitude": 38.4909,
        "longitude": -121.694355,
        "accuracy": "16",
        "context": 0,
        "place_id": "xB7pD8NTUbI3JLZ_",
        "woeid": "2389646",
        "geo_is_family": 0,
        "geo_is_friend": 0,
        "geo_is_contact": 0,
        "geo_is_public": 1,
        "tags": ""
    },
    {
        "id": "8704635217",
        "owner": "7202050@N04",
        "secret": "3b550cf422",
        "server": "8550",
        "farm": 9,
        "title": "Gray Flycatcher",
        "ispublic": 1,
        "isfriend": 0,
        "isfamily": 0,
        "latitude": 38.491538,
        "longitude": -121.694462,
        "accuracy": "16",
        "context": 0,
        "place_id": "xB7pD8NTUbI3JLZ_",
        "woeid": "2389646",
        "geo_is_family": 0,
        "geo_is_friend": 0,
        "geo_is_contact": 0,
        "geo_is_public": 1,
        "tags": ""
    },
    {
        "id": "8157012351",
        "owner": "8552398@N03",
        "secret": "01ec65b7be",
        "server": "8346",
        "farm": 9,
        "title": "Doppel Doppler?",
        "ispublic": 1,
        "isfriend": 0,
        "isfamily": 0,
        "latitude": 38.501665,
        "longitude": -121.686383,
        "accuracy": "16",
        "context": 0,
        "place_id": "xB7pD8NTUbI3JLZ_",
        "woeid": "2389646",
        "geo_is_family": 0,
        "geo_is_friend": 0,
        "geo_is_contact": 0,
        "geo_is_public": 1,
        "tags": ""
    }
]