[
    {
        "id": "8884536882",
        "owner": "26817835@N00",
        "secret": "5982be9e48",
        "server": "7391",
        "farm": 8,
        "title": "",
        "ispublic": 1,
        "isfriend": 0,
        "isfamily": 0,
        "latitude": 38.931083,
        "longitude": -123.420525,
        "accuracy": "16",
        "context": 0,
        "place_id": "Wpfc.o9TVr6gkGuv",
        "woeid": "2440292",
        "geo_is_family": 0,
        "geo_is_friend": 0,
        "geo_is_contact": 0,
        "geo_is_public": 1,
        "tags": "palmdale dryden oskarmile"
    },
    {
        "id": "8149365491",
        "owner": "9743896@N05",
        "secret": "065d7fb7da",
        "server": "8464",
        "farm": 9,
        "title": "Camera Roll-96",
        "ispublic": 1,
        "isfriend": 0,
        "isfamily": 0,
        "latitude": 38.944833,
        "longitude": -123.5545,
        "accuracy": "16",
        "context": 0,
        "place_id": "ILx.3jZQUL.tm1v9LA",
        "woeid": "12587692",
        "geo_is_family": 0,
        "geo_is_friend": 0,
        "geo_is_contact": 0,
        "geo_is_public": 1,
        "tags": ""
    },
    {
        "id": "8149399888",
        "owner": "9743896@N05",
        "secret": "bb190b9e4d",
        "server": "8045",
        "farm": 9,
        "title": "Camera Roll-98",
        "ispublic": 1,
        "isfriend": 0,
        "isfamily": 0,
        "latitude": 38.96,
        "longitude": -123.527833,
        "accuracy": "16",
        "context": 0,
        "place_id": "ILx.3jZQUL.tm1v9LA",
        "woeid": "12587692",
        "geo_is_family": 0,
        "geo_is_friend": 0,
        "geo_is_contact": 0,
        "geo_is_public": 1,
        "tags": ""
    }
]