[
    {
        "id": "9410131165",
        "owner": "90832417@N00",
        "secret": "4468a0b947",
        "server": "5536",
        "farm": 6,
        "title": "Anya and Collin's new stilts made by Tim.",
        "ispublic": 1,
        "isfriend": 0,
        "isfamily": 0,
        "latitude": 32.851166,
        "longitude": -116.891501,
        "accuracy": "16",
        "context": 0,
        "place_id": "GQQfMDtUV7P8ivAJhA",
        "woeid": "55969422",
        "geo_is_family": 0,
        "geo_is_friend": 0,
        "geo_is_contact": 0,
        "geo_is_public": 1,
        "tags": ""
    },
    {
        "id": "9410113043",
        "owner": "90832417@N00",
        "secret": "85c06b097e",
        "server": "5477",
        "farm": 6,
        "title": "Anya and Collin's new stilts made by Tim.",
        "ispublic": 1,
        "isfriend": 0,
        "isfamily": 0,
        "latitude": 32.851166,
        "longitude": -116.891501,
        "accuracy": "16",
        "context": 0,
        "place_id": "GQQfMDtUV7P8ivAJhA",
        "woeid": "55969422",
        "geo_is_family": 0,
        "geo_is_friend": 0,
        "geo_is_contact": 0,
        "geo_is_public": 1,
        "tags": ""
    },
    {
        "id": "8691700824",
        "owner": "29715180@N08",
        "secret": "e234d8cae0",
        "server": "8545",
        "farm": 9,
        "title": "",
        "ispublic": 1,
        "isfriend": 0,
        "isfamily": 0,
        "latitude": 32.865197,
        "longitude": -116.884923,
        "accuracy": "16",
        "context": 0,
        "place_id": "GQQfMDtUV7P8ivAJhA",
        "woeid": "55969422",
        "geo_is_family": 0,
        "geo_is_friend": 0,
        "geo_is_contact": 0,
        "geo_is_public": 1,
        "tags": "california insect unitedstates dragonfly elcajon 2013 lakejennings"
    },
    {
        "id": "8691698798",
        "owner": "29715180@N08",
        "secret": "2fa601c5d5",
        "server": "8406",
        "farm": 9,
        "title": "Bushtit",
        "ispublic": 1,
        "isfriend": 0,
        "isfamily": 0,
        "latitude": 32.860858,
        "longitude": -116.885723,
        "accuracy": "16",
        "context": 0,
        "place_id": "GQQfMDtUV7P8ivAJhA",
        "woeid": "55969422",
        "geo_is_family": 0,
        "geo_is_friend": 0,
        "geo_is_contact": 0,
        "geo_is_public": 1,
        "tags": "california bird unitedstates lakeside bushtit psaltriparusminimus 2013 lakejennings"
    },
    {
        "id": "8691702310",
        "owner": "29715180@N08",
        "secret": "f2dafae14c",
        "server": "8247",
        "farm": 9,
        "title": "Purple Finch",
        "ispublic": 1,
        "isfriend": 0,
        "isfamily": 0,
        "latitude": 32.863141,
        "longitude": -116.888739,
        "accuracy": "16",
        "context": 0,
        "place_id": "GQQfMDtUV7P8ivAJhA",
        "woeid": "55969422",
        "geo_is_family": 0,
        "geo_is_friend": 0,
        "geo_is_contact": 0,
        "geo_is_public": 1,
        "tags": "california bird unitedstates elcajon purplefinch 2013 carpodacuspupureus lakejennings"
    },
    {
        "id": "8691701710",
        "owner": "29715180@N08",
        "secret": "be58ebc20c",
        "server": "8266",
        "farm": 9,
        "title": "Northern Mockingbird",
        "ispublic": 1,
        "isfriend": 0,
        "isfamily": 0,
        "latitude": 32.863141,
        "longitude": -116.888739,
        "accuracy": "16",
        "context": 0,
        "place_id": "GQQfMDtUV7P8ivAJhA",
        "woeid": "55969422",
        "geo_is_family": 0,
        "geo_is_friend": 0,
        "geo_is_contact": 0,
        "geo_is_public": 1,
        "tags": "california bird unitedstates elcajon northernmockingbird mimuspolyglottos 2013 lakejennings"
    },
    {
        "id": "8691698404",
        "owner": "29715180@N08",
        "secret": "d13fb7db6b",
        "server": "8123",
        "farm": 9,
        "title": "Bushtit",
        "ispublic": 1,
        "isfriend": 0,
        "isfamily": 0,
        "latitude": 32.860858,
        "longitude": -116.885723,
        "accuracy": "16",
        "context": 0,
        "place_id": "GQQfMDtUV7P8ivAJhA",
        "woeid": "55969422",
        "geo_is_family": 0,
        "geo_is_friend": 0,
        "geo_is_contact": 0,
        "geo_is_public": 1,
        "tags": "california bird unitedstates lakeside bushtit psaltriparusminimus 2013 lakejennings"
    },
    {
        "id": "8559918388",
        "owner": "47593397@N06",
        "secret": "8fa8723683",
        "server": "8226",
        "farm": 9,
        "title": "Clear.",
        "ispublic": 1,
        "isfriend": 0,
        "isfamily": 0,
        "latitude": 32.853166,
        "longitude": -116.88615,
        "accuracy": "16",
        "context": 0,
        "place_id": "7nz92kpTVrlBQolp",
        "woeid": "2435417",
        "geo_is_family": 0,
        "geo_is_friend": 0,
        "geo_is_contact": 0,
        "geo_is_public": 1,
        "tags": "walking lakeside clearthemind"
    },
    {
        "id": "8504986366",
        "owner": "47593397@N06",
        "secret": "29bca85957",
        "server": "8239",
        "farm": 9,
        "title": "Short Sunday Walk",
        "ispublic": 1,
        "isfriend": 0,
        "isfamily": 0,
        "latitude": 32.853106,
        "longitude": -116.888437,
        "accuracy": "16",
        "context": 0,
        "place_id": "GQQfMDtUV7P8ivAJhA",
        "woeid": "55969422",
        "geo_is_family": 0,
        "geo_is_friend": 0,
        "geo_is_contact": 0,
        "geo_is_public": 1,
        "tags": "lakejennings uploaded:by=flickrmobile flickriosapp:filter=nofilter"
    }
]