[
    {
        "id": "8044713619",
        "owner": "36392134@N00",
        "secret": "871dfb3de2",
        "server": "8175",
        "farm": 9,
        "title": "Farm Sanctuary skyline",
        "ispublic": 1,
        "isfriend": 0,
        "isfamily": 0,
        "latitude": 39.824166,
        "longitude": -122.3305,
        "accuracy": "16",
        "context": 0,
        "place_id": "K7dUWiBQUL9zv1RM2g",
        "woeid": "12587721",
        "geo_is_family": 0,
        "geo_is_friend": 0,
        "geo_is_contact": 0,
        "geo_is_public": 1,
        "tags": "lifeaccordingtocellphone ashleybeyer wwwashleybeyercom"
    },
    {
        "id": "8044712619",
        "owner": "36392134@N00",
        "secret": "7339004b42",
        "server": "8029",
        "farm": 9,
        "title": "Farm Sanctuary",
        "ispublic": 1,
        "isfriend": 0,
        "isfamily": 0,
        "latitude": 39.825,
        "longitude": -122.326167,
        "accuracy": "16",
        "context": 0,
        "place_id": "K7dUWiBQUL9zv1RM2g",
        "woeid": "12587721",
        "geo_is_family": 0,
        "geo_is_friend": 0,
        "geo_is_contact": 0,
        "geo_is_public": 1,
        "tags": "lifeaccordingtocellphone ashleybeyer wwwashleybeyercom"
    },
    {
        "id": "8044713343",
        "owner": "36392134@N00",
        "secret": "726b5d340d",
        "server": "8032",
        "farm": 9,
        "title": "Farm Sanctuary",
        "ispublic": 1,
        "isfriend": 0,
        "isfamily": 0,
        "latitude": 39.823833,
        "longitude": -122.325334,
        "accuracy": "16",
        "context": 0,
        "place_id": "K7dUWiBQUL9zv1RM2g",
        "woeid": "12587721",
        "geo_is_family": 0,
        "geo_is_friend": 0,
        "geo_is_contact": 0,
        "geo_is_public": 1,
        "tags": "lifeaccordingtocellphone ashleybeyer wwwashleybeyercom"
    },
    {
        "id": "8044721236",
        "owner": "36392134@N00",
        "secret": "2a6570d8be",
        "server": "8172",
        "farm": 9,
        "title": "Farm Sanctuary",
        "ispublic": 1,
        "isfriend": 0,
        "isfamily": 0,
        "latitude": 39.824666,
        "longitude": -122.324667,
        "accuracy": "16",
        "context": 0,
        "place_id": "K7dUWiBQUL9zv1RM2g",
        "woeid": "12587721",
        "geo_is_family": 0,
        "geo_is_friend": 0,
        "geo_is_contact": 0,
        "geo_is_public": 1,
        "tags": "lifeaccordingtocellphone ashleybeyer wwwashleybeyercom"
    }
]