[
    {
        "id": "9277779639",
        "owner": "50075111@N00",
        "secret": "482606c2af",
        "server": "3829",
        "farm": 4,
        "title": "Nice camping spot at Del Valle",
        "ispublic": 1,
        "isfriend": 0,
        "isfamily": 0,
        "latitude": 37.568324,
        "longitude": -121.687101,
        "accuracy": "16",
        "context": 0,
        "place_id": "8uOFk5VTVr7XHR5u",
        "woeid": "2449388",
        "geo_is_family": 0,
        "geo_is_friend": 0,
        "geo_is_contact": 0,
        "geo_is_public": 1,
        "tags": "square squareformat mayfair iphoneography instagramapp uploaded:by=instagram foursquare:venue=513bec7d21c6ded336b4ea12"
    },
    {
        "id": "9021009939",
        "owner": "93467796@N03",
        "secret": "7bfd1c299f",
        "server": "5341",
        "farm": 6,
        "title": "Livermore",
        "ispublic": 1,
        "isfriend": 0,
        "isfamily": 0,
        "latitude": 37.583783,
        "longitude": -121.693253,
        "accuracy": "16",
        "context": 0,
        "place_id": "8uOFk5VTVr7XHR5u",
        "woeid": "2449388",
        "geo_is_family": 0,
        "geo_is_friend": 0,
        "geo_is_contact": 0,
        "geo_is_public": 1,
        "tags": ""
    },
    {
        "id": "8694831962",
        "owner": "15463022@N02",
        "secret": "6bed4c6f50",
        "server": "8265",
        "farm": 9,
        "title": "Del Valle Lake Camping",
        "ispublic": 1,
        "isfriend": 0,
        "isfamily": 0,
        "latitude": 37.577601,
        "longitude": -121.69384,
        "accuracy": "16",
        "context": 0,
        "place_id": "8uOFk5VTVr7XHR5u",
        "woeid": "2449388",
        "geo_is_family": 0,
        "geo_is_friend": 0,
        "geo_is_contact": 0,
        "geo_is_public": 1,
        "tags": "uploaded:by=flickrmobile flickriosapp:filter=nofilter"
    },
    {
        "id": "8693719947",
        "owner": "15463022@N02",
        "secret": "1173a871cf",
        "server": "8115",
        "farm": 9,
        "title": "Del Valle Lake Camping",
        "ispublic": 1,
        "isfriend": 0,
        "isfamily": 0,
        "latitude": 37.5845,
        "longitude": -121.7,
        "accuracy": "16",
        "context": 0,
        "place_id": "8uOFk5VTVr7XHR5u",
        "woeid": "2449388",
        "geo_is_family": 0,
        "geo_is_friend": 0,
        "geo_is_contact": 0,
        "geo_is_public": 1,
        "tags": "uploaded:by=flickrmobile flickriosapp:filter=nofilter"
    },
    {
        "id": "8693711727",
        "owner": "15463022@N02",
        "secret": "000b7bf9d1",
        "server": "8534",
        "farm": 9,
        "title": "Del Valle Lake Camping",
        "ispublic": 1,
        "isfriend": 0,
        "isfamily": 0,
        "latitude": 37.577601,
        "longitude": -121.69384,
        "accuracy": "16",
        "context": 0,
        "place_id": "8uOFk5VTVr7XHR5u",
        "woeid": "2449388",
        "geo_is_family": 0,
        "geo_is_friend": 0,
        "geo_is_contact": 0,
        "geo_is_public": 1,
        "tags": "uploaded:by=flickrmobile flickriosapp:filter=nofilter"
    },
    {
        "id": "8693715617",
        "owner": "15463022@N02",
        "secret": "0376e0984c",
        "server": "8405",
        "farm": 9,
        "title": "Del Valle Lake Camping",
        "ispublic": 1,
        "isfriend": 0,
        "isfamily": 0,
        "latitude": 37.577601,
        "longitude": -121.69384,
        "accuracy": "16",
        "context": 0,
        "place_id": "8uOFk5VTVr7XHR5u",
        "woeid": "2449388",
        "geo_is_family": 0,
        "geo_is_friend": 0,
        "geo_is_contact": 0,
        "geo_is_public": 1,
        "tags": "uploaded:by=flickrmobile flickriosapp:filter=nofilter"
    },
    {
        "id": "8694834608",
        "owner": "15463022@N02",
        "secret": "f07a5aeaf9",
        "server": "8539",
        "farm": 9,
        "title": "Del Valle Lake Camping",
        "ispublic": 1,
        "isfriend": 0,
        "isfamily": 0,
        "latitude": 37.577601,
        "longitude": -121.69384,
        "accuracy": "16",
        "context": 0,
        "place_id": "8uOFk5VTVr7XHR5u",
        "woeid": "2449388",
        "geo_is_family": 0,
        "geo_is_friend": 0,
        "geo_is_contact": 0,
        "geo_is_public": 1,
        "tags": "uploaded:by=flickrmobile flickriosapp:filter=nofilter"
    },
    {
        "id": "8693718059",
        "owner": "15463022@N02",
        "secret": "4e16a18e00",
        "server": "8395",
        "farm": 9,
        "title": "Del Valle Lake Camping",
        "ispublic": 1,
        "isfriend": 0,
        "isfamily": 0,
        "latitude": 37.577601,
        "longitude": -121.69384,
        "accuracy": "16",
        "context": 0,
        "place_id": "8uOFk5VTVr7XHR5u",
        "woeid": "2449388",
        "geo_is_family": 0,
        "geo_is_friend": 0,
        "geo_is_contact": 0,
        "geo_is_public": 1,
        "tags": "uploaded:by=flickrmobile flickriosapp:filter=nofilter"
    },
    {
        "id": "8694842892",
        "owner": "15463022@N02",
        "secret": "34c0ea9c56",
        "server": "8403",
        "farm": 9,
        "title": "Del Valle Lake Camping",
        "ispublic": 1,
        "isfriend": 0,
        "isfamily": 0,
        "latitude": 37.584166,
        "longitude": -121.699667,
        "accuracy": "16",
        "context": 0,
        "place_id": "8uOFk5VTVr7XHR5u",
        "woeid": "2449388",
        "geo_is_family": 0,
        "geo_is_friend": 0,
        "geo_is_contact": 0,
        "geo_is_public": 1,
        "tags": "uploaded:by=flickrmobile flickriosapp:filter=nofilter"
    },
    {
        "id": "8693716177",
        "owner": "15463022@N02",
        "secret": "bb6d72b5ff",
        "server": "8540",
        "farm": 9,
        "title": "Del Valle Lake Camping",
        "ispublic": 1,
        "isfriend": 0,
        "isfamily": 0,
        "latitude": 37.577601,
        "longitude": -121.69384,
        "accuracy": "16",
        "context": 0,
        "place_id": "8uOFk5VTVr7XHR5u",
        "woeid": "2449388",
        "geo_is_family": 0,
        "geo_is_friend": 0,
        "geo_is_contact": 0,
        "geo_is_public": 1,
        "tags": "uploaded:by=flickrmobile flickriosapp:filter=nofilter"
    },
    {
        "id": "8693709501",
        "owner": "15463022@N02",
        "secret": "b400cfd6df",
        "server": "8406",
        "farm": 9,
        "title": "Del Valle Lake Camping",
        "ispublic": 1,
        "isfriend": 0,
        "isfamily": 0,
        "latitude": 37.577601,
        "longitude": -121.69384,
        "accuracy": "16",
        "context": 0,
        "place_id": "8uOFk5VTVr7XHR5u",
        "woeid": "2449388",
        "geo_is_family": 0,
        "geo_is_friend": 0,
        "geo_is_contact": 0,
        "geo_is_public": 1,
        "tags": "uploaded:by=flickrmobile flickriosapp:filter=nofilter"
    },
    {
        "id": "8693711249",
        "owner": "15463022@N02",
        "secret": "48a1d033ee",
        "server": "8258",
        "farm": 9,
        "title": "Del Valle Lake Camping",
        "ispublic": 1,
        "isfriend": 0,
        "isfamily": 0,
        "latitude": 37.577601,
        "longitude": -121.69384,
        "accuracy": "16",
        "context": 0,
        "place_id": "8uOFk5VTVr7XHR5u",
        "woeid": "2449388",
        "geo_is_family": 0,
        "geo_is_friend": 0,
        "geo_is_contact": 0,
        "geo_is_public": 1,
        "tags": "uploaded:by=flickrmobile flickriosapp:filter=nofilter"
    },
    {
        "id": "8693710709",
        "owner": "15463022@N02",
        "secret": "045fab4787",
        "server": "8400",
        "farm": 9,
        "title": "Del Valle Lake Camping",
        "ispublic": 1,
        "isfriend": 0,
        "isfamily": 0,
        "latitude": 37.577601,
        "longitude": -121.69384,
        "accuracy": "16",
        "context": 0,
        "place_id": "8uOFk5VTVr7XHR5u",
        "woeid": "2449388",
        "geo_is_family": 0,
        "geo_is_friend": 0,
        "geo_is_contact": 0,
        "geo_is_public": 1,
        "tags": "uploaded:by=flickrmobile flickriosapp:filter=nofilter"
    },
    {
        "id": "8694829838",
        "owner": "15463022@N02",
        "secret": "d993350b62",
        "server": "8116",
        "farm": 9,
        "title": "Del Valle Lake Camping",
        "ispublic": 1,
        "isfriend": 0,
        "isfamily": 0,
        "latitude": 37.577601,
        "longitude": -121.69384,
        "accuracy": "16",
        "context": 0,
        "place_id": "8uOFk5VTVr7XHR5u",
        "woeid": "2449388",
        "geo_is_family": 0,
        "geo_is_friend": 0,
        "geo_is_contact": 0,
        "geo_is_public": 1,
        "tags": "uploaded:by=flickrmobile flickriosapp:filter=nofilter"
    },
    {
        "id": "8694832452",
        "owner": "15463022@N02",
        "secret": "fe6b5db729",
        "server": "8266",
        "farm": 9,
        "title": "Del Valle Lake Camping",
        "ispublic": 1,
        "isfriend": 0,
        "isfamily": 0,
        "latitude": 37.577601,
        "longitude": -121.69384,
        "accuracy": "16",
        "context": 0,
        "place_id": "8uOFk5VTVr7XHR5u",
        "woeid": "2449388",
        "geo_is_family": 0,
        "geo_is_friend": 0,
        "geo_is_contact": 0,
        "geo_is_public": 1,
        "tags": "uploaded:by=flickrmobile flickriosapp:filter=nofilter"
    },
    {
        "id": "8694843246",
        "owner": "15463022@N02",
        "secret": "b0cdb468cf",
        "server": "8404",
        "farm": 9,
        "title": "Del Valle Lake Camping",
        "ispublic": 1,
        "isfriend": 0,
        "isfamily": 0,
        "latitude": 37.584333,
        "longitude": -121.699667,
        "accuracy": "16",
        "context": 0,
        "place_id": "8uOFk5VTVr7XHR5u",
        "woeid": "2449388",
        "geo_is_family": 0,
        "geo_is_friend": 0,
        "geo_is_contact": 0,
        "geo_is_public": 1,
        "tags": "uploaded:by=flickrmobile flickriosapp:filter=nofilter"
    },
    {
        "id": "8694832892",
        "owner": "15463022@N02",
        "secret": "c37885b84b",
        "server": "8540",
        "farm": 9,
        "title": "Del Valle Lake Camping",
        "ispublic": 1,
        "isfriend": 0,
        "isfamily": 0,
        "latitude": 37.577601,
        "longitude": -121.69384,
        "accuracy": "16",
        "context": 0,
        "place_id": "8uOFk5VTVr7XHR5u",
        "woeid": "2449388",
        "geo_is_family": 0,
        "geo_is_friend": 0,
        "geo_is_contact": 0,
        "geo_is_public": 1,
        "tags": "uploaded:by=flickrmobile flickriosapp:filter=nofilter"
    },
    {
        "id": "8694837222",
        "owner": "15463022@N02",
        "secret": "b1a9b9de3e",
        "server": "8120",
        "farm": 9,
        "title": "Del Valle Lake Camping",
        "ispublic": 1,
        "isfriend": 0,
        "isfamily": 0,
        "latitude": 37.5865,
        "longitude": -121.703,
        "accuracy": "16",
        "context": 0,
        "place_id": "8uOFk5VTVr7XHR5u",
        "woeid": "2449388",
        "geo_is_family": 0,
        "geo_is_friend": 0,
        "geo_is_contact": 0,
        "geo_is_public": 1,
        "tags": "uploaded:by=flickrmobile flickriosapp:filter=nofilter"
    },
    {
        "id": "8694837718",
        "owner": "15463022@N02",
        "secret": "8969bcbeff",
        "server": "8122",
        "farm": 9,
        "title": "Del Valle Lake Camping",
        "ispublic": 1,
        "isfriend": 0,
        "isfamily": 0,
        "latitude": 37.586333,
        "longitude": -121.703167,
        "accuracy": "16",
        "context": 0,
        "place_id": "8uOFk5VTVr7XHR5u",
        "woeid": "2449388",
        "geo_is_family": 0,
        "geo_is_friend": 0,
        "geo_is_contact": 0,
        "geo_is_public": 1,
        "tags": "uploaded:by=flickrmobile flickriosapp:filter=nofilter"
    },
    {
        "id": "8693715045",
        "owner": "15463022@N02",
        "secret": "4f626c4b70",
        "server": "8542",
        "farm": 9,
        "title": "Del Valle Lake Camping",
        "ispublic": 1,
        "isfriend": 0,
        "isfamily": 0,
        "latitude": 37.577601,
        "longitude": -121.69384,
        "accuracy": "16",
        "context": 0,
        "place_id": "8uOFk5VTVr7XHR5u",
        "woeid": "2449388",
        "geo_is_family": 0,
        "geo_is_friend": 0,
        "geo_is_contact": 0,
        "geo_is_public": 1,
        "tags": "uploaded:by=flickrmobile flickriosapp:filter=nofilter"
    },
    {
        "id": "8693719451",
        "owner": "15463022@N02",
        "secret": "6ef2e3a04f",
        "server": "8402",
        "farm": 9,
        "title": "Del Valle Lake Camping",
        "ispublic": 1,
        "isfriend": 0,
        "isfamily": 0,
        "latitude": 37.5845,
        "longitude": -121.7,
        "accuracy": "16",
        "context": 0,
        "place_id": "8uOFk5VTVr7XHR5u",
        "woeid": "2449388",
        "geo_is_family": 0,
        "geo_is_friend": 0,
        "geo_is_contact": 0,
        "geo_is_public": 1,
        "tags": "uploaded:by=flickrmobile flickriosapp:filter=nofilter"
    },
    {
        "id": "8694843934",
        "owner": "15463022@N02",
        "secret": "96e30ab3ee",
        "server": "8406",
        "farm": 9,
        "title": "Del Valle Lake Camping",
        "ispublic": 1,
        "isfriend": 0,
        "isfamily": 0,
        "latitude": 37.584166,
        "longitude": -121.6995,
        "accuracy": "16",
        "context": 0,
        "place_id": "8uOFk5VTVr7XHR5u",
        "woeid": "2449388",
        "geo_is_family": 0,
        "geo_is_friend": 0,
        "geo_is_contact": 0,
        "geo_is_public": 1,
        "tags": "uploaded:by=flickrmobile flickriosapp:filter=nofilter"
    },
    {
        "id": "8694843572",
        "owner": "15463022@N02",
        "secret": "9356af8012",
        "server": "8543",
        "farm": 9,
        "title": "Del Valle Lake Camping",
        "ispublic": 1,
        "isfriend": 0,
        "isfamily": 0,
        "latitude": 37.584333,
        "longitude": -121.699667,
        "accuracy": "16",
        "context": 0,
        "place_id": "8uOFk5VTVr7XHR5u",
        "woeid": "2449388",
        "geo_is_family": 0,
        "geo_is_friend": 0,
        "geo_is_contact": 0,
        "geo_is_public": 1,
        "tags": "uploaded:by=flickrmobile flickriosapp:filter=nofilter"
    },
    {
        "id": "8693719003",
        "owner": "15463022@N02",
        "secret": "458f9d9aaa",
        "server": "8401",
        "farm": 9,
        "title": "Del Valle Lake Camping",
        "ispublic": 1,
        "isfriend": 0,
        "isfamily": 0,
        "latitude": 37.584833,
        "longitude": -121.700334,
        "accuracy": "16",
        "context": 0,
        "place_id": "8uOFk5VTVr7XHR5u",
        "woeid": "2449388",
        "geo_is_family": 0,
        "geo_is_friend": 0,
        "geo_is_contact": 0,
        "geo_is_public": 1,
        "tags": "uploaded:by=flickrmobile flickriosapp:filter=nofilter"
    },
    {
        "id": "8693722483",
        "owner": "15463022@N02",
        "secret": "e69fbf3937",
        "server": "8544",
        "farm": 9,
        "title": "Del Valle Lake Camping",
        "ispublic": 1,
        "isfriend": 0,
        "isfamily": 0,
        "latitude": 37.5845,
        "longitude": -121.699834,
        "accuracy": "16",
        "context": 0,
        "place_id": "8uOFk5VTVr7XHR5u",
        "woeid": "2449388",
        "geo_is_family": 0,
        "geo_is_friend": 0,
        "geo_is_contact": 0,
        "geo_is_public": 1,
        "tags": "uploaded:by=flickrmobile flickriosapp:filter=nofilter"
    },
    {
        "id": "8694836724",
        "owner": "15463022@N02",
        "secret": "c74c154da7",
        "server": "8118",
        "farm": 9,
        "title": "Del Valle Lake Camping",
        "ispublic": 1,
        "isfriend": 0,
        "isfamily": 0,
        "latitude": 37.5865,
        "longitude": -121.703,
        "accuracy": "16",
        "context": 0,
        "place_id": "8uOFk5VTVr7XHR5u",
        "woeid": "2449388",
        "geo_is_family": 0,
        "geo_is_friend": 0,
        "geo_is_contact": 0,
        "geo_is_public": 1,
        "tags": "uploaded:by=flickrmobile flickriosapp:filter=nofilter"
    },
    {
        "id": "8693710353",
        "owner": "15463022@N02",
        "secret": "3c460d6c5a",
        "server": "8117",
        "farm": 9,
        "title": "Del Valle Lake Camping",
        "ispublic": 1,
        "isfriend": 0,
        "isfamily": 0,
        "latitude": 37.577601,
        "longitude": -121.69384,
        "accuracy": "16",
        "context": 0,
        "place_id": "8uOFk5VTVr7XHR5u",
        "woeid": "2449388",
        "geo_is_family": 0,
        "geo_is_friend": 0,
        "geo_is_contact": 0,
        "geo_is_public": 1,
        "tags": "uploaded:by=flickrmobile flickriosapp:filter=nofilter"
    },
    {
        "id": "8693721009",
        "owner": "15463022@N02",
        "secret": "136209c99c",
        "server": "8263",
        "farm": 9,
        "title": "Del Valle Lake Camping",
        "ispublic": 1,
        "isfriend": 0,
        "isfamily": 0,
        "latitude": 37.5845,
        "longitude": -121.699834,
        "accuracy": "16",
        "context": 0,
        "place_id": "8uOFk5VTVr7XHR5u",
        "woeid": "2449388",
        "geo_is_family": 0,
        "geo_is_friend": 0,
        "geo_is_contact": 0,
        "geo_is_public": 1,
        "tags": "uploaded:by=flickrmobile flickriosapp:filter=nofilter"
    },
    {
        "id": "8694841932",
        "owner": "15463022@N02",
        "secret": "bdb3f3c361",
        "server": "8393",
        "farm": 9,
        "title": "Del Valle Lake Camping",
        "ispublic": 1,
        "isfriend": 0,
        "isfamily": 0,
        "latitude": 37.5845,
        "longitude": -121.7,
        "accuracy": "16",
        "context": 0,
        "place_id": "8uOFk5VTVr7XHR5u",
        "woeid": "2449388",
        "geo_is_family": 0,
        "geo_is_friend": 0,
        "geo_is_contact": 0,
        "geo_is_public": 1,
        "tags": "uploaded:by=flickrmobile flickriosapp:filter=nofilter"
    },
    {
        "id": "8694834148",
        "owner": "15463022@N02",
        "secret": "af2e0cf504",
        "server": "8258",
        "farm": 9,
        "title": "Del Valle Lake Camping",
        "ispublic": 1,
        "isfriend": 0,
        "isfamily": 0,
        "latitude": 37.577601,
        "longitude": -121.69384,
        "accuracy": "16",
        "context": 0,
        "place_id": "8uOFk5VTVr7XHR5u",
        "woeid": "2449388",
        "geo_is_family": 0,
        "geo_is_friend": 0,
        "geo_is_contact": 0,
        "geo_is_public": 1,
        "tags": "uploaded:by=flickrmobile flickriosapp:filter=nofilter"
    },
    {
        "id": "8693713375",
        "owner": "15463022@N02",
        "secret": "e58ccc27d8",
        "server": "8402",
        "farm": 9,
        "title": "Del Valle Lake Camping",
        "ispublic": 1,
        "isfriend": 0,
        "isfamily": 0,
        "latitude": 37.577601,
        "longitude": -121.69384,
        "accuracy": "16",
        "context": 0,
        "place_id": "8uOFk5VTVr7XHR5u",
        "woeid": "2449388",
        "geo_is_family": 0,
        "geo_is_friend": 0,
        "geo_is_contact": 0,
        "geo_is_public": 1,
        "tags": "uploaded:by=flickrmobile flickriosapp:filter=nofilter"
    },
    {
        "id": "8693699877",
        "owner": "15463022@N02",
        "secret": "b5e851f1ea",
        "server": "8260",
        "farm": 9,
        "title": "Del Valle Lake Camping",
        "ispublic": 1,
        "isfriend": 0,
        "isfamily": 0,
        "latitude": 37.572125,
        "longitude": -121.688679,
        "accuracy": "16",
        "context": 0,
        "place_id": "8uOFk5VTVr7XHR5u",
        "woeid": "2449388",
        "geo_is_family": 0,
        "geo_is_friend": 0,
        "geo_is_contact": 0,
        "geo_is_public": 1,
        "tags": "uploaded:by=flickrmobile flickriosapp:filter=nofilter"
    },
    {
        "id": "8694826420",
        "owner": "15463022@N02",
        "secret": "c9df23defe",
        "server": "8536",
        "farm": 9,
        "title": "Del Valle Lake Camping",
        "ispublic": 1,
        "isfriend": 0,
        "isfamily": 0,
        "latitude": 37.572125,
        "longitude": -121.688679,
        "accuracy": "16",
        "context": 0,
        "place_id": "8uOFk5VTVr7XHR5u",
        "woeid": "2449388",
        "geo_is_family": 0,
        "geo_is_friend": 0,
        "geo_is_contact": 0,
        "geo_is_public": 1,
        "tags": "uploaded:by=flickrmobile flickriosapp:filter=nofilter"
    },
    {
        "id": "8694821792",
        "owner": "15463022@N02",
        "secret": "499477d7ae",
        "server": "8255",
        "farm": 9,
        "title": "Del Valle Lake Camping",
        "ispublic": 1,
        "isfriend": 0,
        "isfamily": 0,
        "latitude": 37.572125,
        "longitude": -121.688679,
        "accuracy": "16",
        "context": 0,
        "place_id": "8uOFk5VTVr7XHR5u",
        "woeid": "2449388",
        "geo_is_family": 0,
        "geo_is_friend": 0,
        "geo_is_contact": 0,
        "geo_is_public": 1,
        "tags": "uploaded:by=flickrmobile flickriosapp:filter=nofilter"
    },
    {
        "id": "8694822176",
        "owner": "15463022@N02",
        "secret": "77a575d3c4",
        "server": "8117",
        "farm": 9,
        "title": "Del Valle Lake Camping",
        "ispublic": 1,
        "isfriend": 0,
        "isfamily": 0,
        "latitude": 37.572125,
        "longitude": -121.688679,
        "accuracy": "16",
        "context": 0,
        "place_id": "8uOFk5VTVr7XHR5u",
        "woeid": "2449388",
        "geo_is_family": 0,
        "geo_is_friend": 0,
        "geo_is_contact": 0,
        "geo_is_public": 1,
        "tags": "uploaded:by=flickrmobile flickriosapp:filter=nofilter"
    },
    {
        "id": "8693700293",
        "owner": "15463022@N02",
        "secret": "689a5044b7",
        "server": "8400",
        "farm": 9,
        "title": "Del Valle Lake Camping",
        "ispublic": 1,
        "isfriend": 0,
        "isfamily": 0,
        "latitude": 37.572125,
        "longitude": -121.688679,
        "accuracy": "16",
        "context": 0,
        "place_id": "8uOFk5VTVr7XHR5u",
        "woeid": "2449388",
        "geo_is_family": 0,
        "geo_is_friend": 0,
        "geo_is_contact": 0,
        "geo_is_public": 1,
        "tags": "uploaded:by=flickrmobile flickriosapp:filter=nofilter"
    },
    {
        "id": "8693707433",
        "owner": "15463022@N02",
        "secret": "71ecfa33a2",
        "server": "8403",
        "farm": 9,
        "title": "Del Valle Lake Camping",
        "ispublic": 1,
        "isfriend": 0,
        "isfamily": 0,
        "latitude": 37.577601,
        "longitude": -121.69384,
        "accuracy": "16",
        "context": 0,
        "place_id": "8uOFk5VTVr7XHR5u",
        "woeid": "2449388",
        "geo_is_family": 0,
        "geo_is_friend": 0,
        "geo_is_contact": 0,
        "geo_is_public": 1,
        "tags": "uploaded:by=flickrmobile flickriosapp:filter=nofilter"
    },
    {
        "id": "8693705907",
        "owner": "15463022@N02",
        "secret": "200ded092d",
        "server": "8258",
        "farm": 9,
        "title": "Del Valle Lake Camping",
        "ispublic": 1,
        "isfriend": 0,
        "isfamily": 0,
        "latitude": 37.572125,
        "longitude": -121.688679,
        "accuracy": "16",
        "context": 0,
        "place_id": "8uOFk5VTVr7XHR5u",
        "woeid": "2449388",
        "geo_is_family": 0,
        "geo_is_friend": 0,
        "geo_is_contact": 0,
        "geo_is_public": 1,
        "tags": "uploaded:by=flickrmobile flickriosapp:filter=nofilter"
    },
    {
        "id": "8693708711",
        "owner": "15463022@N02",
        "secret": "bedcf66e52",
        "server": "8118",
        "farm": 9,
        "title": "Del Valle Lake Camping",
        "ispublic": 1,
        "isfriend": 0,
        "isfamily": 0,
        "latitude": 37.577601,
        "longitude": -121.69384,
        "accuracy": "16",
        "context": 0,
        "place_id": "8uOFk5VTVr7XHR5u",
        "woeid": "2449388",
        "geo_is_family": 0,
        "geo_is_friend": 0,
        "geo_is_contact": 0,
        "geo_is_public": 1,
        "tags": "uploaded:by=flickrmobile flickriosapp:filter=nofilter"
    },
    {
        "id": "8693705443",
        "owner": "15463022@N02",
        "secret": "f3b68b844a",
        "server": "8118",
        "farm": 9,
        "title": "Del Valle Lake Camping",
        "ispublic": 1,
        "isfriend": 0,
        "isfamily": 0,
        "latitude": 37.572125,
        "longitude": -121.688679,
        "accuracy": "16",
        "context": 0,
        "place_id": "8uOFk5VTVr7XHR5u",
        "woeid": "2449388",
        "geo_is_family": 0,
        "geo_is_friend": 0,
        "geo_is_contact": 0,
        "geo_is_public": 1,
        "tags": "uploaded:by=flickrmobile flickriosapp:filter=nofilter"
    },
    {
        "id": "8694823450",
        "owner": "15463022@N02",
        "secret": "7646a63dfd",
        "server": "8538",
        "farm": 9,
        "title": "Del Valle Lake Camping",
        "ispublic": 1,
        "isfriend": 0,
        "isfamily": 0,
        "latitude": 37.572125,
        "longitude": -121.688679,
        "accuracy": "16",
        "context": 0,
        "place_id": "8uOFk5VTVr7XHR5u",
        "woeid": "2449388",
        "geo_is_family": 0,
        "geo_is_friend": 0,
        "geo_is_contact": 0,
        "geo_is_public": 1,
        "tags": "uploaded:by=flickrmobile flickriosapp:filter=nofilter"
    },
    {
        "id": "8694821340",
        "owner": "15463022@N02",
        "secret": "52f9940397",
        "server": "8534",
        "farm": 9,
        "title": "Del Valle Lake Camping",
        "ispublic": 1,
        "isfriend": 0,
        "isfamily": 0,
        "latitude": 37.572125,
        "longitude": -121.688679,
        "accuracy": "16",
        "context": 0,
        "place_id": "8uOFk5VTVr7XHR5u",
        "woeid": "2449388",
        "geo_is_family": 0,
        "geo_is_friend": 0,
        "geo_is_contact": 0,
        "geo_is_public": 1,
        "tags": "uploaded:by=flickrmobile flickriosapp:filter=nofilter"
    },
    {
        "id": "8693703803",
        "owner": "15463022@N02",
        "secret": "19963007b0",
        "server": "8123",
        "farm": 9,
        "title": "Del Valle Lake Camping",
        "ispublic": 1,
        "isfriend": 0,
        "isfamily": 0,
        "latitude": 37.572125,
        "longitude": -121.688679,
        "accuracy": "16",
        "context": 0,
        "place_id": "8uOFk5VTVr7XHR5u",
        "woeid": "2449388",
        "geo_is_family": 0,
        "geo_is_friend": 0,
        "geo_is_contact": 0,
        "geo_is_public": 1,
        "tags": "uploaded:by=flickrmobile flickriosapp:filter=nofilter"
    },
    {
        "id": "8693703015",
        "owner": "15463022@N02",
        "secret": "45683cc4b2",
        "server": "8403",
        "farm": 9,
        "title": "Del Valle Lake Camping",
        "ispublic": 1,
        "isfriend": 0,
        "isfamily": 0,
        "latitude": 37.572125,
        "longitude": -121.688679,
        "accuracy": "16",
        "context": 0,
        "place_id": "8uOFk5VTVr7XHR5u",
        "woeid": "2449388",
        "geo_is_family": 0,
        "geo_is_friend": 0,
        "geo_is_contact": 0,
        "geo_is_public": 1,
        "tags": "uploaded:by=flickrmobile flickriosapp:filter=nofilter"
    },
    {
        "id": "8693707807",
        "owner": "15463022@N02",
        "secret": "8302877675",
        "server": "8117",
        "farm": 9,
        "title": "Del Valle Lake Camping",
        "ispublic": 1,
        "isfriend": 0,
        "isfamily": 0,
        "latitude": 37.577601,
        "longitude": -121.69384,
        "accuracy": "16",
        "context": 0,
        "place_id": "8uOFk5VTVr7XHR5u",
        "woeid": "2449388",
        "geo_is_family": 0,
        "geo_is_friend": 0,
        "geo_is_contact": 0,
        "geo_is_public": 1,
        "tags": "uploaded:by=flickrmobile flickriosapp:filter=nofilter"
    },
    {
        "id": "8693706931",
        "owner": "15463022@N02",
        "secret": "ab1c0ff73a",
        "server": "8256",
        "farm": 9,
        "title": "Del Valle Lake Camping",
        "ispublic": 1,
        "isfriend": 0,
        "isfamily": 0,
        "latitude": 37.572125,
        "longitude": -121.688679,
        "accuracy": "16",
        "context": 0,
        "place_id": "8uOFk5VTVr7XHR5u",
        "woeid": "2449388",
        "geo_is_family": 0,
        "geo_is_friend": 0,
        "geo_is_contact": 0,
        "geo_is_public": 1,
        "tags": "uploaded:by=flickrmobile flickriosapp:filter=nofilter"
    },
    {
        "id": "8693705029",
        "owner": "15463022@N02",
        "secret": "ce675b0644",
        "server": "8545",
        "farm": 9,
        "title": "Del Valle Lake Camping",
        "ispublic": 1,
        "isfriend": 0,
        "isfamily": 0,
        "latitude": 37.572125,
        "longitude": -121.688679,
        "accuracy": "16",
        "context": 0,
        "place_id": "8uOFk5VTVr7XHR5u",
        "woeid": "2449388",
        "geo_is_family": 0,
        "geo_is_friend": 0,
        "geo_is_contact": 0,
        "geo_is_public": 1,
        "tags": "uploaded:by=flickrmobile flickriosapp:filter=nofilter"
    },
    {
        "id": "8694824752",
        "owner": "15463022@N02",
        "secret": "406074841b",
        "server": "8119",
        "farm": 9,
        "title": "Del Valle Lake Camping",
        "ispublic": 1,
        "isfriend": 0,
        "isfamily": 0,
        "latitude": 37.572125,
        "longitude": -121.688679,
        "accuracy": "16",
        "context": 0,
        "place_id": "8uOFk5VTVr7XHR5u",
        "woeid": "2449388",
        "geo_is_family": 0,
        "geo_is_friend": 0,
        "geo_is_contact": 0,
        "geo_is_public": 1,
        "tags": "uploaded:by=flickrmobile flickriosapp:filter=nofilter"
    },
    {
        "id": "8693702611",
        "owner": "15463022@N02",
        "secret": "99af00566e",
        "server": "8406",
        "farm": 9,
        "title": "Del Valle Lake Camping",
        "ispublic": 1,
        "isfriend": 0,
        "isfamily": 0,
        "latitude": 37.572125,
        "longitude": -121.688679,
        "accuracy": "16",
        "context": 0,
        "place_id": "8uOFk5VTVr7XHR5u",
        "woeid": "2449388",
        "geo_is_family": 0,
        "geo_is_friend": 0,
        "geo_is_contact": 0,
        "geo_is_public": 1,
        "tags": "uploaded:by=flickrmobile flickriosapp:filter=nofilter"
    },
    {
        "id": "8694820888",
        "owner": "15463022@N02",
        "secret": "27227e493f",
        "server": "8543",
        "farm": 9,
        "title": "Del Valle Lake Camping",
        "ispublic": 1,
        "isfriend": 0,
        "isfamily": 0,
        "latitude": 37.572125,
        "longitude": -121.688679,
        "accuracy": "16",
        "context": 0,
        "place_id": "8uOFk5VTVr7XHR5u",
        "woeid": "2449388",
        "geo_is_family": 0,
        "geo_is_friend": 0,
        "geo_is_contact": 0,
        "geo_is_public": 1,
        "tags": "uploaded:by=flickrmobile flickriosapp:filter=nofilter"
    },
    {
        "id": "8694824340",
        "owner": "15463022@N02",
        "secret": "62752a4b2f",
        "server": "8543",
        "farm": 9,
        "title": "Del Valle Lake Camping",
        "ispublic": 1,
        "isfriend": 0,
        "isfamily": 0,
        "latitude": 37.572125,
        "longitude": -121.688679,
        "accuracy": "16",
        "context": 0,
        "place_id": "8uOFk5VTVr7XHR5u",
        "woeid": "2449388",
        "geo_is_family": 0,
        "geo_is_friend": 0,
        "geo_is_contact": 0,
        "geo_is_public": 1,
        "tags": "uploaded:by=flickrmobile flickriosapp:filter=nofilter"
    },
    {
        "id": "8694817852",
        "owner": "15463022@N02",
        "secret": "bd8e80ae94",
        "server": "8403",
        "farm": 9,
        "title": "Del Valle Lake Camping",
        "ispublic": 1,
        "isfriend": 0,
        "isfamily": 0,
        "latitude": 37.572125,
        "longitude": -121.688679,
        "accuracy": "16",
        "context": 0,
        "place_id": "8uOFk5VTVr7XHR5u",
        "woeid": "2449388",
        "geo_is_family": 0,
        "geo_is_friend": 0,
        "geo_is_contact": 0,
        "geo_is_public": 1,
        "tags": "uploaded:by=flickrmobile flickriosapp:filter=nofilter"
    },
    {
        "id": "8693700635",
        "owner": "15463022@N02",
        "secret": "d18aaf262b",
        "server": "8399",
        "farm": 9,
        "title": "Del Valle Lake Camping",
        "ispublic": 1,
        "isfriend": 0,
        "isfamily": 0,
        "latitude": 37.572125,
        "longitude": -121.688679,
        "accuracy": "16",
        "context": 0,
        "place_id": "8uOFk5VTVr7XHR5u",
        "woeid": "2449388",
        "geo_is_family": 0,
        "geo_is_friend": 0,
        "geo_is_contact": 0,
        "geo_is_public": 1,
        "tags": "uploaded:by=flickrmobile flickriosapp:filter=nofilter"
    },
    {
        "id": "8694818298",
        "owner": "15463022@N02",
        "secret": "e33699e868",
        "server": "8535",
        "farm": 9,
        "title": "Del Valle Lake Camping",
        "ispublic": 1,
        "isfriend": 0,
        "isfamily": 0,
        "latitude": 37.572125,
        "longitude": -121.688679,
        "accuracy": "16",
        "context": 0,
        "place_id": "8uOFk5VTVr7XHR5u",
        "woeid": "2449388",
        "geo_is_family": 0,
        "geo_is_friend": 0,
        "geo_is_contact": 0,
        "geo_is_public": 1,
        "tags": "uploaded:by=flickrmobile flickriosapp:filter=nofilter"
    },
    {
        "id": "8693699479",
        "owner": "15463022@N02",
        "secret": "cd104232d1",
        "server": "8545",
        "farm": 9,
        "title": "Del Valle Lake Camping",
        "ispublic": 1,
        "isfriend": 0,
        "isfamily": 0,
        "latitude": 37.572125,
        "longitude": -121.688679,
        "accuracy": "16",
        "context": 0,
        "place_id": "8uOFk5VTVr7XHR5u",
        "woeid": "2449388",
        "geo_is_family": 0,
        "geo_is_friend": 0,
        "geo_is_contact": 0,
        "geo_is_public": 1,
        "tags": "uploaded:by=flickrmobile flickriosapp:filter=nofilter"
    },
    {
        "id": "8694819014",
        "owner": "15463022@N02",
        "secret": "2fab0b6900",
        "server": "8545",
        "farm": 9,
        "title": "Del Valle Lake Camping",
        "ispublic": 1,
        "isfriend": 0,
        "isfamily": 0,
        "latitude": 37.572125,
        "longitude": -121.688679,
        "accuracy": "16",
        "context": 0,
        "place_id": "8uOFk5VTVr7XHR5u",
        "woeid": "2449388",
        "geo_is_family": 0,
        "geo_is_friend": 0,
        "geo_is_contact": 0,
        "geo_is_public": 1,
        "tags": "uploaded:by=flickrmobile flickriosapp:filter=nofilter"
    },
    {
        "id": "8691062404",
        "owner": "15463022@N02",
        "secret": "5268696f52",
        "server": "7050",
        "farm": 8,
        "title": "Del Valle Lake",
        "ispublic": 1,
        "isfriend": 0,
        "isfamily": 0,
        "latitude": 37.584,
        "longitude": -121.699167,
        "accuracy": "16",
        "context": 0,
        "place_id": "8uOFk5VTVr7XHR5u",
        "woeid": "2449388",
        "geo_is_family": 0,
        "geo_is_friend": 0,
        "geo_is_contact": 0,
        "geo_is_public": 1,
        "tags": "uploaded:by=flickrmobile flickriosapp:filter=nofilter"
    },
    {
        "id": "8689941615",
        "owner": "15463022@N02",
        "secret": "5247616e81",
        "server": "8536",
        "farm": 9,
        "title": "Del Valle Lake",
        "ispublic": 1,
        "isfriend": 0,
        "isfamily": 0,
        "latitude": 37.584166,
        "longitude": -121.6995,
        "accuracy": "16",
        "context": 0,
        "place_id": "8uOFk5VTVr7XHR5u",
        "woeid": "2449388",
        "geo_is_family": 0,
        "geo_is_friend": 0,
        "geo_is_contact": 0,
        "geo_is_public": 1,
        "tags": "uploaded:by=flickrmobile flickriosapp:filter=nofilter"
    },
    {
        "id": "8689940767",
        "owner": "15463022@N02",
        "secret": "3930426a81",
        "server": "7043",
        "farm": 8,
        "title": "Del Valle Lake",
        "ispublic": 1,
        "isfriend": 0,
        "isfamily": 0,
        "latitude": 37.586833,
        "longitude": -121.702834,
        "accuracy": "16",
        "context": 0,
        "place_id": "8uOFk5VTVr7XHR5u",
        "woeid": "2449388",
        "geo_is_family": 0,
        "geo_is_friend": 0,
        "geo_is_contact": 0,
        "geo_is_public": 1,
        "tags": "uploaded:by=flickrmobile flickriosapp:filter=nofilter"
    },
    {
        "id": "8678908405",
        "owner": "46734275@N00",
        "secret": "6d1972186e",
        "server": "8406",
        "farm": 9,
        "title": "Fluffy",
        "ispublic": 1,
        "isfriend": 0,
        "isfamily": 0,
        "latitude": 37.586367,
        "longitude": -121.703313,
        "accuracy": "16",
        "context": 0,
        "place_id": "8uOFk5VTVr7XHR5u",
        "woeid": "2449388",
        "geo_is_family": 0,
        "geo_is_friend": 0,
        "geo_is_contact": 0,
        "geo_is_public": 1,
        "tags": "bird livermore darkeyedjunco delvalle project65 delvalleregionalpark ebparksok"
    },
    {
        "id": "8546034240",
        "owner": "65806304@N05",
        "secret": "188961083c",
        "server": "8105",
        "farm": 9,
        "title": "",
        "ispublic": 1,
        "isfriend": 0,
        "isfamily": 0,
        "latitude": 37.562,
        "longitude": -121.709167,
        "accuracy": "16",
        "context": 0,
        "place_id": "1IvHpmpQUL8ZId.pmA",
        "woeid": "12587670",
        "geo_is_family": 0,
        "geo_is_friend": 0,
        "geo_is_contact": 0,
        "geo_is_public": 1,
        "tags": ""
    },
    {
        "id": "8544923595",
        "owner": "65806304@N05",
        "secret": "a71bb77804",
        "server": "8389",
        "farm": 9,
        "title": "",
        "ispublic": 1,
        "isfriend": 0,
        "isfamily": 0,
        "latitude": 37.560833,
        "longitude": -121.708167,
        "accuracy": "16",
        "context": 0,
        "place_id": "1IvHpmpQUL8ZId.pmA",
        "woeid": "12587670",
        "geo_is_family": 0,
        "geo_is_friend": 0,
        "geo_is_contact": 0,
        "geo_is_public": 1,
        "tags": ""
    },
    {
        "id": "8526257799",
        "owner": "65806304@N05",
        "secret": "3667259ac3",
        "server": "8392",
        "farm": 9,
        "title": "",
        "ispublic": 1,
        "isfriend": 0,
        "isfamily": 0,
        "latitude": 37.575166,
        "longitude": -121.698834,
        "accuracy": "16",
        "context": 0,
        "place_id": "8uOFk5VTVr7XHR5u",
        "woeid": "2449388",
        "geo_is_family": 0,
        "geo_is_friend": 0,
        "geo_is_contact": 0,
        "geo_is_public": 1,
        "tags": "uploaded:by=flickrmobile flickriosapp:filter=nofilter"
    },
    {
        "id": "8469162081",
        "owner": "18244673@N00",
        "secret": "7e38b5302c",
        "server": "8388",
        "farm": 9,
        "title": "Spider",
        "ispublic": 1,
        "isfriend": 0,
        "isfamily": 0,
        "latitude": 37.585398,
        "longitude": -121.697396,
        "accuracy": "16",
        "context": 0,
        "place_id": "8uOFk5VTVr7XHR5u",
        "woeid": "2449388",
        "geo_is_family": 0,
        "geo_is_friend": 0,
        "geo_is_contact": 0,
        "geo_is_public": 1,
        "tags": "spider delvalleregionalpark canonmpe65mmf2815xmacrophoto canonmacroringlitemr14ex"
    },
    {
        "id": "8440752787",
        "owner": "69597679@N00",
        "secret": "7c9da193aa",
        "server": "8187",
        "farm": 9,
        "title": "Steller's Jay (Cyanocitta stelleri)",
        "ispublic": 1,
        "isfriend": 0,
        "isfamily": 0,
        "latitude": 37.568715,
        "longitude": -121.685485,
        "accuracy": "16",
        "context": 0,
        "place_id": "NsbUWfBTUb4mbyVu",
        "woeid": "2347563",
        "geo_is_family": 0,
        "geo_is_friend": 0,
        "geo_is_contact": 0,
        "geo_is_public": 1,
        "tags": "stellersjay cyanocittastelleri delvalleregionalpark"
    },
    {
        "id": "8440752875",
        "owner": "69597679@N00",
        "secret": "47ea0a03aa",
        "server": "8079",
        "farm": 9,
        "title": "Western Scrub Jay (Aphelocoma californica)",
        "ispublic": 1,
        "isfriend": 0,
        "isfamily": 0,
        "latitude": 37.567595,
        "longitude": -121.68663,
        "accuracy": "16",
        "context": 0,
        "place_id": "NsbUWfBTUb4mbyVu",
        "woeid": "2347563",
        "geo_is_family": 0,
        "geo_is_friend": 0,
        "geo_is_contact": 0,
        "geo_is_public": 1,
        "tags": "westernscrubjay aphelocomacalifornica delvalleregionalpark"
    },
    {
        "id": "8440764353",
        "owner": "69597679@N00",
        "secret": "44e1aaa138",
        "server": "8216",
        "farm": 9,
        "title": "Steller's Jay (Cyanocitta stelleri)",
        "ispublic": 1,
        "isfriend": 0,
        "isfamily": 0,
        "latitude": 37.568468,
        "longitude": -121.684849,
        "accuracy": "16",
        "context": 0,
        "place_id": "NsbUWfBTUb4mbyVu",
        "woeid": "2347563",
        "geo_is_family": 0,
        "geo_is_friend": 0,
        "geo_is_contact": 0,
        "geo_is_public": 1,
        "tags": "stellersjay cyanocittastelleri delvalleregionalpark"
    },
    {
        "id": "8438534470",
        "owner": "69597679@N00",
        "secret": "315f803358",
        "server": "8371",
        "farm": 9,
        "title": "Yellow-billed Magpie (Pica nuttalli)",
        "ispublic": 1,
        "isfriend": 0,
        "isfamily": 0,
        "latitude": 37.568383,
        "longitude": -121.685539,
        "accuracy": "16",
        "context": 0,
        "place_id": "NsbUWfBTUb4mbyVu",
        "woeid": "2347563",
        "geo_is_family": 0,
        "geo_is_friend": 0,
        "geo_is_contact": 0,
        "geo_is_public": 1,
        "tags": "livermore yellowbilledmagpie picanuttalli delvalleregionalpark delvallelake"
    },
    {
        "id": "8438534408",
        "owner": "69597679@N00",
        "secret": "8b81880459",
        "server": "8084",
        "farm": 9,
        "title": "Yellow-billed Magpie (Pica nuttalli)",
        "ispublic": 1,
        "isfriend": 0,
        "isfamily": 0,
        "latitude": 37.568258,
        "longitude": -121.685496,
        "accuracy": "16",
        "context": 0,
        "place_id": "NsbUWfBTUb4mbyVu",
        "woeid": "2347563",
        "geo_is_family": 0,
        "geo_is_friend": 0,
        "geo_is_contact": 0,
        "geo_is_public": 1,
        "tags": "livermore yellowbilledmagpie picanuttalli delvalleregionalpark delvallelake"
    },
    {
        "id": "8437450665",
        "owner": "69597679@N00",
        "secret": "af10b0f456",
        "server": "8233",
        "farm": 9,
        "title": "Yellow-billed Magpie (Pica nuttalli)",
        "ispublic": 1,
        "isfriend": 0,
        "isfamily": 0,
        "latitude": 37.568132,
        "longitude": -121.685412,
        "accuracy": "16",
        "context": 0,
        "place_id": "NsbUWfBTUb4mbyVu",
        "woeid": "2347563",
        "geo_is_family": 0,
        "geo_is_friend": 0,
        "geo_is_contact": 0,
        "geo_is_public": 1,
        "tags": "livermore yellowbilledmagpie picanuttalli delvalleregionalpark delvallelake"
    },
    {
        "id": "8341521687",
        "owner": "58008645@N00",
        "secret": "55b4405c28",
        "server": "8224",
        "farm": 9,
        "title": "American Crow",
        "ispublic": 1,
        "isfriend": 0,
        "isfamily": 0,
        "latitude": 37.585685,
        "longitude": -121.698721,
        "accuracy": "16",
        "context": 0,
        "place_id": "8uOFk5VTVr7XHR5u",
        "woeid": "2449388",
        "geo_is_family": 0,
        "geo_is_friend": 0,
        "geo_is_contact": 0,
        "geo_is_public": 1,
        "tags": "birds americancrow delvalleregionalpark 5dmarkiiiand1dxflightshots"
    },
    {
        "id": "8341163540",
        "owner": "18244673@N00",
        "secret": "4770c6a112",
        "server": "8501",
        "farm": 9,
        "title": "2/365  Greedy crow",
        "ispublic": 1,
        "isfriend": 0,
        "isfamily": 0,
        "latitude": 37.586724,
        "longitude": -121.702562,
        "accuracy": "16",
        "context": 0,
        "place_id": "8uOFk5VTVr7XHR5u",
        "woeid": "2449388",
        "geo_is_family": 0,
        "geo_is_friend": 0,
        "geo_is_contact": 0,
        "geo_is_public": 1,
        "tags": "peanut crow mittromney project365 delvalleregionalpark canonef600mmf4lisusm"
    },
    {
        "id": "8341111490",
        "owner": "18244673@N00",
        "secret": "50ffc030d3",
        "server": "8499",
        "farm": 9,
        "title": "Deer",
        "ispublic": 1,
        "isfriend": 0,
        "isfamily": 0,
        "latitude": 37.586503,
        "longitude": -121.700695,
        "accuracy": "16",
        "context": 0,
        "place_id": "8uOFk5VTVr7XHR5u",
        "woeid": "2449388",
        "geo_is_family": 0,
        "geo_is_friend": 0,
        "geo_is_contact": 0,
        "geo_is_public": 1,
        "tags": "deer delvalleregionalpark canonef600mmf4lisusm"
    },
    {
        "id": "8340051887",
        "owner": "18244673@N00",
        "secret": "17c29e909d",
        "server": "8216",
        "farm": 9,
        "title": "Woodpecker",
        "ispublic": 1,
        "isfriend": 0,
        "isfamily": 0,
        "latitude": 37.58266,
        "longitude": -121.691254,
        "accuracy": "16",
        "context": 0,
        "place_id": "8uOFk5VTVr7XHR5u",
        "woeid": "2449388",
        "geo_is_family": 0,
        "geo_is_friend": 0,
        "geo_is_contact": 0,
        "geo_is_public": 1,
        "tags": "woodpecker delvalleregionalpark canonef600mmf4lisusm"
    },
    {
        "id": "8340052273",
        "owner": "18244673@N00",
        "secret": "fb4990538d",
        "server": "8501",
        "farm": 9,
        "title": "Angus steer",
        "ispublic": 1,
        "isfriend": 0,
        "isfamily": 0,
        "latitude": 37.585449,
        "longitude": -121.697541,
        "accuracy": "16",
        "context": 0,
        "place_id": "8uOFk5VTVr7XHR5u",
        "woeid": "2449388",
        "geo_is_family": 0,
        "geo_is_friend": 0,
        "geo_is_contact": 0,
        "geo_is_public": 1,
        "tags": "angus steer delvalleregionalpark canonef600mmf4lisusm"
    },
    {
        "id": "8341001384",
        "owner": "58008645@N00",
        "secret": "b5844bcb9d",
        "server": "8498",
        "farm": 9,
        "title": "Acorn Woodpecker",
        "ispublic": 1,
        "isfriend": 0,
        "isfamily": 0,
        "latitude": 37.585719,
        "longitude": -121.698678,
        "accuracy": "16",
        "context": 0,
        "place_id": "8uOFk5VTVr7XHR5u",
        "woeid": "2449388",
        "geo_is_family": 0,
        "geo_is_friend": 0,
        "geo_is_contact": 0,
        "geo_is_public": 1,
        "tags": "birds moo alamedacounty acornwoodpecker delvalleregionalpark 5dmarkiiiand1dxflightshots"
    },
    {
        "id": "8341001490",
        "owner": "58008645@N00",
        "secret": "37053d609c",
        "server": "8355",
        "farm": 9,
        "title": "A dark day",
        "ispublic": 1,
        "isfriend": 0,
        "isfamily": 0,
        "latitude": 37.585651,
        "longitude": -121.698764,
        "accuracy": "16",
        "context": 0,
        "place_id": "8uOFk5VTVr7XHR5u",
        "woeid": "2449388",
        "geo_is_family": 0,
        "geo_is_friend": 0,
        "geo_is_contact": 0,
        "geo_is_public": 1,
        "tags": "birds magpies alamedacounty yellowbilledmagpie delvalleregionalpark 5dmarkiiiand1dxflightshots"
    },
    {
        "id": "8341001460",
        "owner": "58008645@N00",
        "secret": "3e3bb84893",
        "server": "8361",
        "farm": 9,
        "title": "A dark day",
        "ispublic": 1,
        "isfriend": 0,
        "isfamily": 0,
        "latitude": 37.585736,
        "longitude": -121.698635,
        "accuracy": "16",
        "context": 0,
        "place_id": "8uOFk5VTVr7XHR5u",
        "woeid": "2449388",
        "geo_is_family": 0,
        "geo_is_friend": 0,
        "geo_is_contact": 0,
        "geo_is_public": 1,
        "tags": "birds magpies alamedacounty yellowbilledmagpie delvalleregionalpark"
    },
    {
        "id": "7910587524",
        "owner": "17187387@N04",
        "secret": "534e9ec6d3",
        "server": "8316",
        "farm": 9,
        "title": "Del Valle, Livermore",
        "ispublic": 1,
        "isfriend": 0,
        "isfamily": 0,
        "latitude": 37.589677,
        "longitude": -121.704098,
        "accuracy": "16",
        "context": 0,
        "place_id": "8uOFk5VTVr7XHR5u",
        "woeid": "2449388",
        "geo_is_family": 0,
        "geo_is_friend": 0,
        "geo_is_contact": 0,
        "geo_is_public": 1,
        "tags": "california unitedstates livermore"
    },
    {
        "id": "8693713819",
        "owner": "15463022@N02",
        "secret": "9fe14f7754",
        "server": "8124",
        "farm": 9,
        "title": "Del Valle Lake Camping",
        "ispublic": 1,
        "isfriend": 0,
        "isfamily": 0,
        "latitude": 37.577601,
        "longitude": -121.69384,
        "accuracy": "16",
        "context": 0,
        "place_id": "8uOFk5VTVr7XHR5u",
        "woeid": "2449388",
        "geo_is_family": 0,
        "geo_is_friend": 0,
        "geo_is_contact": 0,
        "geo_is_public": 1,
        "tags": "uploaded:by=flickrmobile flickriosapp:filter=nofilter"
    },
    {
        "id": "8693709139",
        "owner": "15463022@N02",
        "secret": "7ec528d9e0",
        "server": "8115",
        "farm": 9,
        "title": "Del Valle Lake Camping",
        "ispublic": 1,
        "isfriend": 0,
        "isfamily": 0,
        "latitude": 37.577601,
        "longitude": -121.69384,
        "accuracy": "16",
        "context": 0,
        "place_id": "8uOFk5VTVr7XHR5u",
        "woeid": "2449388",
        "geo_is_family": 0,
        "geo_is_friend": 0,
        "geo_is_contact": 0,
        "geo_is_public": 1,
        "tags": "uploaded:by=flickrmobile flickriosapp:filter=nofilter"
    },
    {
        "id": "8694828138",
        "owner": "15463022@N02",
        "secret": "b85a41198a",
        "server": "8255",
        "farm": 9,
        "title": "Del Valle Lake Camping",
        "ispublic": 1,
        "isfriend": 0,
        "isfamily": 0,
        "latitude": 37.577601,
        "longitude": -121.69384,
        "accuracy": "16",
        "context": 0,
        "place_id": "8uOFk5VTVr7XHR5u",
        "woeid": "2449388",
        "geo_is_family": 0,
        "geo_is_friend": 0,
        "geo_is_contact": 0,
        "geo_is_public": 1,
        "tags": "uploaded:by=flickrmobile flickriosapp:filter=nofilter"
    }
]