[
    {
        "id": "8509877216",
        "owner": "19186305@N00",
        "secret": "f5b7d60942",
        "server": "8383",
        "farm": 9,
        "title": "130216_05motion",
        "ispublic": 1,
        "isfriend": 0,
        "isfamily": 0,
        "latitude": 38.066524,
        "longitude": -122.587455,
        "accuracy": "16",
        "context": 0,
        "place_id": "t.VfQA1UV7PPgyeb_w",
        "woeid": "55970185",
        "geo_is_family": 0,
        "geo_is_friend": 0,
        "geo_is_contact": 0,
        "geo_is_public": 1,
        "tags": "california ca square novato weeks 52 fiftytwo 52weeks 52weeksprocess"
    },
    {
        "id": "8508770479",
        "owner": "19186305@N00",
        "secret": "16077ecbc5",
        "server": "8110",
        "farm": 9,
        "title": "130216_01slow",
        "ispublic": 1,
        "isfriend": 0,
        "isfamily": 0,
        "latitude": 38.066524,
        "longitude": -122.587455,
        "accuracy": "16",
        "context": 0,
        "place_id": "t.VfQA1UV7PPgyeb_w",
        "woeid": "55970185",
        "geo_is_family": 0,
        "geo_is_friend": 0,
        "geo_is_contact": 0,
        "geo_is_public": 1,
        "tags": "california ca square novato weeks 52 iphone fiftytwo mobileupload 52weeks iphoneography instagram instagramapp appleiphone4s averagecamerapro avgcampro averagecameraproapp vscocam vscocamapp avgcamproapp 52weeksprocess"
    },
    {
        "id": "8495723199",
        "owner": "19186305@N00",
        "secret": "116cee2a31",
        "server": "8242",
        "farm": 9,
        "title": "130216_02star",
        "ispublic": 1,
        "isfriend": 0,
        "isfamily": 0,
        "latitude": 38.066524,
        "longitude": -122.587455,
        "accuracy": "16",
        "context": 0,
        "place_id": "t.VfQA1UV7PPgyeb_w",
        "woeid": "55970185",
        "geo_is_family": 0,
        "geo_is_friend": 0,
        "geo_is_contact": 0,
        "geo_is_public": 1,
        "tags": "california ca square novato weeks 52 iphone dodecatheonhendersonii fiftytwo mobileupload 52weeks iphoneography instagram instagramapp appleiphone4s vscocam vscocamapp uploaded:by=flickrmobile flickriosapp:filter=nofilter 52weeksprocess"
    },
    {
        "id": "8495722667",
        "owner": "19186305@N00",
        "secret": "03b1cafa06",
        "server": "8245",
        "farm": 9,
        "title": "130216_01kate",
        "ispublic": 1,
        "isfriend": 0,
        "isfamily": 0,
        "latitude": 38.066524,
        "longitude": -122.587455,
        "accuracy": "16",
        "context": 0,
        "place_id": "t.VfQA1UV7PPgyeb_w",
        "woeid": "55970185",
        "geo_is_family": 0,
        "geo_is_friend": 0,
        "geo_is_contact": 0,
        "geo_is_public": 1,
        "tags": "california ca square novato weeks 52 iphone fiftytwo mobileupload 52weeks iphoneography instagram instagramapp appleiphone4s vscocam vscocamapp uploaded:by=flickrmobile flickriosapp:filter=nofilter 52weeksprocess"
    }
]