[
    {
        "id": "9167004093",
        "owner": "71967132@N00",
        "secret": "023506c620",
        "server": "2822",
        "farm": 3,
        "title": "Our trip up the coast was well timed. Current temperature, 78 in the shade. California!",
        "ispublic": 1,
        "isfriend": 0,
        "isfamily": 0,
        "latitude": 39.193059,
        "longitude": -123.754295,
        "accuracy": "16",
        "context": 0,
        "place_id": "OtlTGuhTUb9qVEJf",
        "woeid": "2352764",
        "geo_is_family": 0,
        "geo_is_friend": 0,
        "geo_is_contact": 0,
        "geo_is_public": 1,
        "tags": "square squareformat mayfair iphoneography instagramapp uploaded:by=instagram foursquare:venue=500aea22e4b01d293bbe9e77"
    },
    {
        "id": "8990766455",
        "owner": "98652717@N00",
        "secret": "69eefcc40b",
        "server": "5463",
        "farm": 6,
        "title": "",
        "ispublic": 1,
        "isfriend": 0,
        "isfamily": 0,
        "latitude": 39.156333,
        "longitude": -123.629167,
        "accuracy": "16",
        "context": 0,
        "place_id": "47YWSHRTUb0AUeBR",
        "woeid": "2374646",
        "geo_is_family": 0,
        "geo_is_friend": 0,
        "geo_is_contact": 0,
        "geo_is_public": 1,
        "tags": "uploaded:by=flickrmobile flickriosapp:filter=nofilter"
    },
    {
        "id": "8991964264",
        "owner": "98652717@N00",
        "secret": "1bb1534a61",
        "server": "7350",
        "farm": 8,
        "title": "",
        "ispublic": 1,
        "isfriend": 0,
        "isfamily": 0,
        "latitude": 39.156166,
        "longitude": -123.629,
        "accuracy": "16",
        "context": 0,
        "place_id": "47YWSHRTUb0AUeBR",
        "woeid": "2374646",
        "geo_is_family": 0,
        "geo_is_friend": 0,
        "geo_is_contact": 0,
        "geo_is_public": 1,
        "tags": "uploaded:by=flickrmobile flickriosapp:filter=nofilter"
    },
    {
        "id": "8991965794",
        "owner": "98652717@N00",
        "secret": "ff59b3a05b",
        "server": "2865",
        "farm": 3,
        "title": "",
        "ispublic": 1,
        "isfriend": 0,
        "isfamily": 0,
        "latitude": 39.156,
        "longitude": -123.6295,
        "accuracy": "16",
        "context": 0,
        "place_id": "47YWSHRTUb0AUeBR",
        "woeid": "2374646",
        "geo_is_family": 0,
        "geo_is_friend": 0,
        "geo_is_contact": 0,
        "geo_is_public": 1,
        "tags": "uploaded:by=flickrmobile flickriosapp:filter=nofilter"
    },
    {
        "id": "8990259699",
        "owner": "28276801@N02",
        "secret": "87f6f436a3",
        "server": "2869",
        "farm": 3,
        "title": "One-Eyed Willy",
        "ispublic": 1,
        "isfriend": 0,
        "isfamily": 0,
        "latitude": 39.16439,
        "longitude": -123.73882,
        "accuracy": "16",
        "context": 0,
        "place_id": "Vpx0ZatTUbNeZcqG",
        "woeid": "2398368",
        "geo_is_family": 0,
        "geo_is_friend": 0,
        "geo_is_contact": 0,
        "geo_is_public": 1,
        "tags": "ocean california trip usa canon rocks powershot oceano scogli unitedstateofamerica a810 lux76 fogliluca nobrainstudio"
    },
    {
        "id": "8715726834",
        "owner": "95549746@N08",
        "secret": "d5d67c0b64",
        "server": "7283",
        "farm": 8,
        "title": "navarro",
        "ispublic": 1,
        "isfriend": 0,
        "isfamily": 0,
        "latitude": 39.193665,
        "longitude": -123.757874,
        "accuracy": "16",
        "context": 0,
        "place_id": "OtlTGuhTUb9qVEJf",
        "woeid": "2352764",
        "geo_is_family": 0,
        "geo_is_friend": 0,
        "geo_is_contact": 0,
        "geo_is_public": 1,
        "tags": ""
    },
    {
        "id": "8538541412",
        "owner": "86186036@N00",
        "secret": "d29b65884c",
        "server": "8102",
        "farm": 9,
        "title": "Storm rolling in",
        "ispublic": 1,
        "isfriend": 0,
        "isfamily": 0,
        "latitude": 39.189291,
        "longitude": -123.758583,
        "accuracy": "16",
        "context": 0,
        "place_id": "OtlTGuhTUb9qVEJf",
        "woeid": "2352764",
        "geo_is_family": 0,
        "geo_is_friend": 0,
        "geo_is_contact": 0,
        "geo_is_public": 1,
        "tags": "square squareformat mayfair iphoneography instagramapp uploaded:by=instagram foursquare:venue=4f52c3b9e4b0d3a8f51c2d8e"
    },
    {
        "id": "8432760528",
        "owner": "43667163@N00",
        "secret": "d1a42a3079",
        "server": "8230",
        "farm": 9,
        "title": "",
        "ispublic": 1,
        "isfriend": 0,
        "isfamily": 0,
        "latitude": 39.169666,
        "longitude": -123.744,
        "accuracy": "16",
        "context": 0,
        "place_id": "Vpx0ZatTUbNeZcqG",
        "woeid": "2398368",
        "geo_is_family": 0,
        "geo_is_friend": 0,
        "geo_is_contact": 0,
        "geo_is_public": 1,
        "tags": ""
    },
    {
        "id": "8431675165",
        "owner": "43667163@N00",
        "secret": "c2996f9912",
        "server": "8230",
        "farm": 9,
        "title": "",
        "ispublic": 1,
        "isfriend": 0,
        "isfamily": 0,
        "latitude": 39.169666,
        "longitude": -123.744,
        "accuracy": "16",
        "context": 0,
        "place_id": "Vpx0ZatTUbNeZcqG",
        "woeid": "2398368",
        "geo_is_family": 0,
        "geo_is_friend": 0,
        "geo_is_contact": 0,
        "geo_is_public": 1,
        "tags": ""
    },
    {
        "id": "8405023064",
        "owner": "91620953@N07",
        "secret": "f3ae61efcd",
        "server": "8498",
        "farm": 9,
        "title": "California and shit.",
        "ispublic": 1,
        "isfriend": 0,
        "isfamily": 0,
        "latitude": 39.164333,
        "longitude": -123.738834,
        "accuracy": "16",
        "context": 0,
        "place_id": "Vpx0ZatTUbNeZcqG",
        "woeid": "2398368",
        "geo_is_family": 0,
        "geo_is_friend": 0,
        "geo_is_contact": 0,
        "geo_is_public": 1,
        "tags": "uploaded:by=flickrmobile flickriosapp:filter=orangutan orangutanfilter"
    },
    {
        "id": "8405032556",
        "owner": "91620953@N07",
        "secret": "0db92455b9",
        "server": "8515",
        "farm": 9,
        "title": "California and shit.",
        "ispublic": 1,
        "isfriend": 0,
        "isfamily": 0,
        "latitude": 39.1645,
        "longitude": -123.738834,
        "accuracy": "16",
        "context": 0,
        "place_id": "Vpx0ZatTUbNeZcqG",
        "woeid": "2398368",
        "geo_is_family": 0,
        "geo_is_friend": 0,
        "geo_is_contact": 0,
        "geo_is_public": 1,
        "tags": "uploaded:by=flickrmobile flickriosapp:filter=mammoth mammothfilter"
    },
    {
        "id": "8263019723",
        "owner": "11227239@N05",
        "secret": "4656cd143b",
        "server": "8348",
        "farm": 9,
        "title": "Sea Cave, Navarro Beach, California",
        "ispublic": 1,
        "isfriend": 0,
        "isfamily": 0,
        "latitude": 39.191811,
        "longitude": -123.763467,
        "accuracy": "16",
        "context": 0,
        "place_id": "OtlTGuhTUb9qVEJf",
        "woeid": "2352764",
        "geo_is_family": 0,
        "geo_is_friend": 0,
        "geo_is_contact": 0,
        "geo_is_public": 1,
        "tags": "ocean california county ca sea bw usa white black america river humboldt state pacific north parks navarro cave norcal northern seacave mendoncino"
    },
    {
        "id": "8184716846",
        "owner": "8742248@N07",
        "secret": "ded36f20c0",
        "server": "8479",
        "farm": 9,
        "title": "Mendocino Coast",
        "ispublic": 1,
        "isfriend": 0,
        "isfamily": 0,
        "latitude": 39.180741,
        "longitude": -123.753048,
        "accuracy": "16",
        "context": 0,
        "place_id": "OtlTGuhTUb9qVEJf",
        "woeid": "2352764",
        "geo_is_family": 0,
        "geo_is_friend": 0,
        "geo_is_contact": 0,
        "geo_is_public": 1,
        "tags": "california ca usa unitedstates unitedstatesofamerica"
    },
    {
        "id": "8184716414",
        "owner": "8742248@N07",
        "secret": "af3144efde",
        "server": "8204",
        "farm": 9,
        "title": "Mendocino Coast",
        "ispublic": 1,
        "isfriend": 0,
        "isfamily": 0,
        "latitude": 39.194313,
        "longitude": -123.763775,
        "accuracy": "16",
        "context": 0,
        "place_id": "OtlTGuhTUb9qVEJf",
        "woeid": "2352764",
        "geo_is_family": 0,
        "geo_is_friend": 0,
        "geo_is_contact": 0,
        "geo_is_public": 1,
        "tags": "california ca usa unitedstates unitedstatesofamerica"
    },
    {
        "id": "8085092484",
        "owner": "21040690@N07",
        "secret": "617c9781e1",
        "server": "8193",
        "farm": 9,
        "title": "photo.JPG",
        "ispublic": 1,
        "isfriend": 0,
        "isfamily": 0,
        "latitude": 39.156333,
        "longitude": -123.7345,
        "accuracy": "16",
        "context": 0,
        "place_id": "Vpx0ZatTUbNeZcqG",
        "woeid": "2398368",
        "geo_is_family": 0,
        "geo_is_friend": 0,
        "geo_is_contact": 0,
        "geo_is_public": 1,
        "tags": ""
    },
    {
        "id": "8072856688",
        "owner": "21040690@N07",
        "secret": "8cd1d51d7f",
        "server": "8315",
        "farm": 9,
        "title": "photo.JPG",
        "ispublic": 1,
        "isfriend": 0,
        "isfamily": 0,
        "latitude": 39.156333,
        "longitude": -123.7345,
        "accuracy": "16",
        "context": 0,
        "place_id": "Vpx0ZatTUbNeZcqG",
        "woeid": "2398368",
        "geo_is_family": 0,
        "geo_is_friend": 0,
        "geo_is_contact": 0,
        "geo_is_public": 1,
        "tags": ""
    },
    {
        "id": "8072858532",
        "owner": "21040690@N07",
        "secret": "21281e10b4",
        "server": "8454",
        "farm": 9,
        "title": "This car is pretty awesome ... perfect color too",
        "ispublic": 1,
        "isfriend": 0,
        "isfamily": 0,
        "latitude": 39.156333,
        "longitude": -123.7345,
        "accuracy": "16",
        "context": 0,
        "place_id": "Vpx0ZatTUbNeZcqG",
        "woeid": "2398368",
        "geo_is_family": 0,
        "geo_is_friend": 0,
        "geo_is_contact": 0,
        "geo_is_public": 1,
        "tags": ""
    },
    {
        "id": "9435901659",
        "owner": "71967132@N00",
        "secret": "888ef226bf",
        "server": "2871",
        "farm": 3,
        "title": "Typical Summer morning on the coast. I love that tourist season in the Bay Area is when its the foggiest. April and October, everybody, trust me on this.",
        "ispublic": 1,
        "isfriend": 0,
        "isfamily": 0,
        "latitude": 39.193059,
        "longitude": -123.754295,
        "accuracy": "16",
        "context": 0,
        "place_id": "OtlTGuhTUb9qVEJf",
        "woeid": "2352764",
        "geo_is_family": 0,
        "geo_is_friend": 0,
        "geo_is_contact": 0,
        "geo_is_public": 1,
        "tags": "square squareformat rise iphoneography instagramapp uploaded:by=instagram foursquare:venue=500aea22e4b01d293bbe9e77"
    }
]