{"type":"FeatureCollection","features":[{"type":"Feature","properties":{"agncy_id":1038,"label_name":"Bel Aire Park","own_type":"Fee","unit_name":"Bel Aire Park","agncy_lev":"City","layer":"City","agncy_name":"Burbank, City of","gis_acres":1.78},"geometry":{"type":"MultiPolygon","coordinates":[[[[-118.314594,34.380731],[-118.314725,34.380829],[-118.315099,34.381105],[-118.315142,34.381132],[-118.315208,34.381185],[-118.315351,34.381283],[-118.314795,34.381814],[-118.314049,34.381324],[-118.314594,34.380731]]]]}}]}