{"type":"FeatureCollection","features":[{"type":"Feature","properties":{"agncy_name":"Pinole, City of","unit_name":"Canyon Drive Park","agncy_lev":"City","layer":"City","label_name":"Canyon Drive Park","own_type":"Fee","agncy_id":1252,"gis_acres":0.39},"geometry":{"type":"MultiPolygon","coordinates":[[[[-122.29642364854558,37.99533330854226],[-122.29638132114924,37.995025593814574],[-122.29694317814116,37.99504388271545],[-122.2969403573944,37.995339384315194],[-122.29642364854558,37.99533330854226]]]]}}]}