{"type":"FeatureCollection","features":[{"type":"Feature","properties":{"agncy_name":"Sacramento, County of","unit_name":"Capitol Park","agncy_lev":"County","layer":"County","label_name":"Capitol Park","own_type":"Fee","agncy_id":316,"gis_acres":29.71},"geometry":{"type":"MultiPolygon","coordinates":[[[[-13524660.51638021,4661066.487728522],[-13524552.766761458,4661352.317556895],[-13523946.677306343,4661145.6799374875],[-13524044.838387348,4660856.652054484],[-13524660.51638021,4661066.487728522]]]]}}]}