{"type":"FeatureCollection","features":[{"type":"Feature","properties":{"agncy_id":1249,"label_name":"Case Del Oro Park","own_type":"Fee","unit_name":"Case Del Oro Park","agncy_lev":"City","layer":"City","agncy_name":"Petaluma, City of","gis_acres":2.95},"geometry":{"type":"MultiPolygon","coordinates":[[[[-122.596538,38.424888],[-122.597155,38.423717],[-122.597777,38.424062],[-122.597715,38.424212],[-122.597578,38.424453],[-122.597379,38.424864],[-122.597017,38.425324],[-122.596758,38.42557],[-122.596326,38.425338],[-122.596538,38.424888]]]]}}]}