{"type":"FeatureCollection","features":[{"type":"Feature","properties":{"agncy_name":"Los Angeles, City of","unit_name":"Chevy Chase Park","agncy_lev":"City","layer":"City","label_name":"Chevy Chase Park","own_type":"Fee","agncy_id":1188,"gis_acres":1.18},"geometry":{"type":"MultiPolygon","coordinates":[[[[-13165335.455954233,4046745.1680098353],[-13165421.170407703,4046745.311805273],[-13165423.635080952,4046847.15717226],[-13165371.717404762,4046846.5909452564],[-13165335.455954233,4046745.1680098353]]]]}}]}