{"type":"FeatureCollection","features":[{"type":"Feature","properties":{"agncy_id":1300,"label_name":"Dupont Tennis Courts","own_type":"Fee","unit_name":"Dupont Tennis Courts","agncy_lev":"City","layer":"City","agncy_name":"San Francisco, City and County of","gis_acres":0.82},"geometry":{"type":"MultiPolygon","coordinates":[[[[-122.490684,37.968757],[-122.491231,37.968733],[-122.491261,37.969145],[-122.490847,37.969163],[-122.490435,37.969182],[-122.490405,37.96877],[-122.490684,37.968757]]]]}}]}