{"type":"FeatureCollection","features":[{"type":"Feature","properties":{"agncy_id":1232,"label_name":"George Gibbs Park","own_type":"Fee","unit_name":"George Gibbs Park","agncy_lev":"City","layer":"City","agncy_name":"Ontario, City of","gis_acres":2.89},"geometry":{"type":"MultiPolygon","coordinates":[[[[-117.677767,34.258303],[-117.678428,34.258301],[-117.678428,34.258392],[-117.678435,34.260033],[-117.677774,34.260035],[-117.677769,34.25878],[-117.677768,34.258394],[-117.677767,34.258303]]]]}}]}