{"type":"FeatureCollection","features":[{"type":"Feature","properties":{"agncy_id":2085,"label_name":"Granite Rock Dunes","own_type":"Fee","unit_name":"Granite Rock Dunes","agncy_lev":"Special District","layer":"Special District","agncy_name":"Monterey Peninsula Regional Park District","gis_acres":47.09},"geometry":{"type":"MultiPolygon","coordinates":[[[[-121.80313,36.887402],[-121.804252,36.885927],[-121.804486,36.885662],[-121.804946,36.885195],[-121.805014,36.884925],[-121.805051,36.884849],[-121.806557,36.885458],[-121.807223,36.885727],[-121.809876,36.8868],[-121.809727,36.887813],[-121.809387,36.889938],[-121.804558,36.888254],[-121.80313,36.887402]]]]}}]}