{"type":"FeatureCollection","features":[{"type":"Feature","properties":{"agncy_id":1297,"label_name":"La Jolla Athletic Area","own_type":"Fee","unit_name":"La Jolla Athletic Area","agncy_lev":"City","layer":"City","agncy_name":"San Diego, City of","gis_acres":6.92},"geometry":{"type":"MultiPolygon","coordinates":[[[[-117.242419,33.045387],[-117.243148,33.042129],[-117.243233,33.042138],[-117.244142,33.042127],[-117.244126,33.044298],[-117.242715,33.044283],[-117.242451,33.045459],[-117.242419,33.045432],[-117.242419,33.045387]]]]}}]}