{"type":"FeatureCollection","features":[{"type":"Feature","properties":{"agncy_name":"Rohnert Park, City of","unit_name":"Lilac Way Tot Lot","agncy_lev":"City","layer":"City","label_name":"Lilac Way Tot Lot","own_type":"Fee","agncy_id":1281,"gis_acres":0.16},"geometry":{"type":"MultiPolygon","coordinates":[[[[-13657531.951371118,4625049.078101493],[-13657531.937053585,4625003.8423281545],[-13657554.949750341,4625003.829703604],[-13657554.473413376,4625048.741404799],[-13657531.951371118,4625049.078101493]]]]}}]}