{"type":"FeatureCollection","features":[{"type":"Feature","properties":{"agncy_id":1300,"label_name":"Noe & Beaver Mini Park","own_type":"Fee","unit_name":"Noe & Beaver Mini Park","agncy_lev":"City","layer":"City","agncy_name":"San Francisco, City and County of","gis_acres":0.06},"geometry":{"type":"MultiPolygon","coordinates":[[[[-122.433305,37.951121],[-122.433578,37.951104],[-122.433586,37.951193],[-122.433484,37.9512],[-122.433444,37.951202],[-122.433313,37.95121],[-122.433305,37.951121]]]]}}]}