{"type":"FeatureCollection","features":[{"type":"Feature","properties":{"agncy_id":312,"label_name":"Orange holding 21","own_type":"Fee","unit_name":"Orange holding 21","agncy_lev":"County","layer":"County","agncy_name":"Orange, County of","gis_acres":1.28},"geometry":{"type":"MultiPolygon","coordinates":[[[[-117.633433,33.733597],[-117.633497,33.733588],[-117.633833,33.73383],[-117.633933,33.734191],[-117.633773,33.734536],[-117.633409,33.734737],[-117.633344,33.734719],[-117.633286,33.73415],[-117.633433,33.733597]]]]}}]}