{"type":"FeatureCollection","features":[{"type":"Feature","properties":{"agncy_id":1297,"label_name":"Senior Citizens Center","own_type":"Fee","unit_name":"Senior Citizens Center","agncy_lev":"City","layer":"City","agncy_name":"San Diego, City of","gis_acres":0.49},"geometry":{"type":"MultiPolygon","coordinates":[[[[-117.144153,32.87678],[-117.144295,32.876647],[-117.144731,32.876952],[-117.14477,32.876979],[-117.144975,32.877121],[-117.144785,32.877315],[-117.144771,32.877302],[-117.14456,32.877124],[-117.144153,32.87678]]]]}}]}