{"type":"FeatureCollection","features":[{"type":"Feature","properties":{"agncy_id":1307,"label_name":"Terrace Hill Water Tank","own_type":"Fee","unit_name":"Terrace Hill Water Tank","agncy_lev":"City","layer":"City","agncy_name":"San Luis Obispo, City of","gis_acres":0.44},"geometry":{"type":"MultiPolygon","coordinates":[[[[-120.649747,35.453177],[-120.650027,35.453036],[-120.650039,35.453244],[-120.650227,35.45352],[-120.650282,35.453488],[-120.650484,35.453753],[-120.650144,35.453683],[-120.650074,35.453689],[-120.649747,35.453177]]]]}}]}