{"type":"FeatureCollection","features":[{"type":"Feature","properties":{"agncy_id":1009,"label_name":"Tierra Verde Park","own_type":"Fee","unit_name":"Tierra Verde Park","agncy_lev":"City","layer":"City","agncy_name":"Arcadia, City of","gis_acres":1.54},"geometry":{"type":"MultiPolygon","coordinates":[[[[-118.024145,34.299857],[-118.024752,34.299852],[-118.024752,34.299888],[-118.02476,34.300539],[-118.023849,34.300547],[-118.023843,34.300004],[-118.023842,34.299905],[-118.023939,34.299904],[-118.024135,34.299903],[-118.024145,34.299857]]]]}}]}