{"type":"FeatureCollection","features":[{"type":"Feature","properties":{"agncy_id":2186,"label_name":"Yuba County Water Agency 26","own_type":"Fee","unit_name":"Yuba County Water Agency 26","agncy_lev":"Special District","layer":"Special District","agncy_name":"Yuba County Water Agency","gis_acres":75.9},"geometry":{"type":"MultiPolygon","coordinates":[[[[-121.185846,39.527541],[-121.194145,39.528043],[-121.194155,39.530058],[-121.194162,39.531606],[-121.189059,39.531659],[-121.187698,39.53165],[-121.186733,39.531643],[-121.185764,39.531664],[-121.185846,39.527541]]]]}}]}